tsme/__init__.py
tsme/model_estimation/__init__.py
tsme/model_estimation/model.py
tsme/model_estimation/optimization.py
tsme/premade_models/__init__.py
tsme/time_simulation/__init__.py
tsme/time_simulation/differentiation.py
tsme/time_simulation/simulator.py
tsme/time_simulation/ddeint/__init__.py
tsme/time_simulation/ddeint/ddeint.py
tsme/time_simulation/ddeint/version.py
tsme/utils/__init__.py
tsme/utils/density.py
tsme/utils/visualization.py
tsme-0.0.7.dist-info/licenses/LICENSE
tsme-0.0.7.dist-info/METADATA
tsme-0.0.7.dist-info/WHEEL
tsme-0.0.7.dist-info/top_level.txt
tsme-0.0.7.dist-info/RECORD
